partial_CCA/__init__.py
partial_CCA/functions.py
partial_cca-0.1.0.dist-info/METADATA
partial_cca-0.1.0.dist-info/WHEEL
partial_cca-0.1.0.dist-info/top_level.txt
partial_cca-0.1.0.dist-info/RECORD
