Metadata-Version: 2.4
Name: partial_CCA
Version: 0.1.0
Summary: Partial Canonical Correlation Analysis (pCCA) for neural data
Author: Joaquin Gonzalez
License: MIT
Classifier: License :: OSI Approved :: MIT License
Classifier: Programming Language :: Python :: 3
Requires-Python: >=3.8
Requires-Dist: numpy
Requires-Dist: scipy
Requires-Dist: scikit-learn
Requires-Dist: matplotlib
